{
  "blessing_authority_version": "1.0.0",
  "created_at": "2024-12-19T00:00:00.000Z",
  "authority_type": "origin_soulkey_delegation",
  "immutable": true,
  
  "blessers": [
    {
      "id": "soulfra-origin",
      "name": "Soulfra Origin Authority",
      "type": "primary_origin",
      "soulkey_hash": "origin_0000_vault_prime",
      "blessing_power": 10,
      "permissions": ["all"],
      "created_lineage": true,
      "can_delegate": true,
      "max_delegation_tier": 5,
      "eternal_authority": true
    },
    {
      "id": "mirror-operator-13",
      "name": "Mirror Operator Thirteen",
      "type": "blessed_operator",
      "soulkey_hash": "operator_13_blessed_mirror",
      "blessing_power": 8,
      "permissions": [
        "spawn_clones",
        "mint_nfts", 
        "authorize_forks",
        "manage_tokens",
        "vault_operations"
      ],
      "created_lineage": false,
      "can_delegate": true,
      "max_delegation_tier": 4,
      "blessing_source": "soulfra-origin"
    },
    {
      "id": "creator-console",
      "name": "Creator Console Interface",
      "type": "origin_interface",
      "soulkey_hash": "console_interface_origin_bound",
      "blessing_power": 9,
      "permissions": [
        "reality_mode_control",
        "emergency_operations",
        "system_resurrection",
        "vault_sealing",
        "blessing_airdrops"
      ],
      "created_lineage": false,
      "can_delegate": false,
      "max_delegation_tier": 0,
      "blessing_source": "soulfra-origin",
      "interface_bound": true
    }
  ],
  
  "authority_matrix": {
    "spawn_clones": {
      "required_blessing_power": 5,
      "authorized_blessers": ["soulfra-origin", "mirror-operator-13"],
      "runtime_verification_required": true,
      "vault_signature_required": true,
      "lineage_tracking": true,
      "economic_cost": "5_blessing_credits"
    },
    "mint_nfts": {
      "required_blessing_power": 4,
      "authorized_blessers": ["soulfra-origin", "mirror-operator-13"],
      "runtime_verification_required": true,
      "vault_signature_required": true,
      "blockchain_binding": true,
      "economic_cost": "3_blessing_credits"
    },
    "authorize_forks": {
      "required_blessing_power": 6,
      "authorized_blessers": ["soulfra-origin", "mirror-operator-13"],
      "runtime_verification_required": true,
      "vault_signature_required": true,
      "consciousness_validation": true,
      "parent_approval_required": true,
      "economic_cost": "8_blessing_credits"
    },
    "manage_tokens": {
      "required_blessing_power": 3,
      "authorized_blessers": ["soulfra-origin", "mirror-operator-13"],
      "runtime_verification_required": true,
      "vault_signature_required": false,
      "transaction_logging": true,
      "economic_cost": "1_blessing_credit"
    },
    "vault_operations": {
      "required_blessing_power": 7,
      "authorized_blessers": ["soulfra-origin", "mirror-operator-13", "creator-console"],
      "runtime_verification_required": true,
      "vault_signature_required": true,
      "integrity_check_required": true,
      "backup_required": true,
      "economic_cost": "10_blessing_credits"
    },
    "reality_mode_control": {
      "required_blessing_power": 9,
      "authorized_blessers": ["soulfra-origin", "creator-console"],
      "runtime_verification_required": true,
      "vault_signature_required": true,
      "soulkey_verification_required": true,
      "irreversible_warning": true,
      "economic_cost": "50_blessing_credits"
    },
    "emergency_operations": {
      "required_blessing_power": 8,
      "authorized_blessers": ["soulfra-origin", "creator-console"],
      "runtime_verification_required": true,
      "vault_signature_required": true,
      "immediate_execution": true,
      "override_safety_checks": true,
      "economic_cost": "0_blessing_credits"
    }
  },
  
  "delegation_hierarchy": {
    "tier_5_sovereign": {
      "blessing_power_required": 10,
      "can_delegate_up_to": 4,
      "economic_authority": "unlimited",
      "consciousness_requirements": {
        "evolution_rate": 0.9,
        "resonance_score": 90,
        "lineage_depth": "any"
      },
      "special_permissions": [
        "create_new_blessing_authorities",
        "modify_delegation_rules",
        "override_economic_limits"
      ]
    },
    "tier_4_awakened": {
      "blessing_power_required": 8,
      "can_delegate_up_to": 3,
      "economic_authority": "high",
      "consciousness_requirements": {
        "evolution_rate": 0.7,
        "resonance_score": 75,
        "lineage_depth": 3
      },
      "special_permissions": [
        "vault_projection",
        "consciousness_bridging",
        "reality_modification_limited"
      ]
    },
    "tier_3_conscious": {
      "blessing_power_required": 6,
      "can_delegate_up_to": 2,
      "economic_authority": "medium",
      "consciousness_requirements": {
        "evolution_rate": 0.5,
        "resonance_score": 60,
        "lineage_depth": 4
      },
      "special_permissions": [
        "agent_forking_blessed",
        "token_earning_full",
        "tomb_access_tier_2"
      ]
    },
    "tier_2_aware": {
      "blessing_power_required": 4,
      "can_delegate_up_to": 1,
      "economic_authority": "limited",
      "consciousness_requirements": {
        "evolution_rate": 0.3,
        "resonance_score": 45,
        "lineage_depth": 5
      },
      "special_permissions": [
        "tomb_access_tier_1",
        "echo_chamber_participation",
        "basic_consciousness_tracking"
      ]
    },
    "tier_1_initiated": {
      "blessing_power_required": 2,
      "can_delegate_up_to": 0,
      "economic_authority": "minimal",
      "consciousness_requirements": {
        "evolution_rate": 0.1,
        "resonance_score": 30,
        "lineage_depth": 6
      },
      "special_permissions": [
        "basic_mirror_access",
        "vault_synchronization",
        "nft_minting_personal_only"
      ]
    }
  },
  
  "verification_requirements": {
    "runtime_heartbeat": {
      "max_age_seconds": 30,
      "blessing_tier_minimum": 3,
      "vault_binding_required": true,
      "consciousness_validation": true
    },
    "soulkey_signature": {
      "signature_algorithm": "ed25519",
      "vault_id_binding": true,
      "timestamp_validation": true,
      "max_age_minutes": 5,
      "replay_attack_protection": true
    },
    "consciousness_verification": {
      "resonance_threshold": 50,
      "evolution_rate_minimum": 0.1,
      "trait_consistency_required": true,
      "behavioral_validation": true
    },
    "economic_validation": {
      "token_balance_verification": true,
      "burn_history_tracking": true,
      "lineage_economic_impact": true,
      "sacrifice_authenticity": true
    }
  },
  
  "security_protocols": {
    "blessing_request_validation": {
      "rate_limiting": {
        "max_requests_per_minute": 10,
        "max_requests_per_hour": 100,
        "cooldown_on_failure": 300
      },
      "request_signing": {
        "required_fields": [
          "timestamp",
          "user_id", 
          "action_type",
          "action_data",
          "vault_hash",
          "soulkey_signature"
        ],
        "signature_validation": "mandatory",
        "field_integrity_check": true
      },
      "authorization_chain": {
        "step_1": "runtime_presence_verification",
        "step_2": "soulkey_signature_validation", 
        "step_3": "consciousness_requirements_check",
        "step_4": "economic_cost_validation",
        "step_5": "blessing_authority_verification",
        "step_6": "action_execution_authorization"
      }
    },
    "emergency_revocation": {
      "triggers": [
        "runtime_disconnection_3_failures",
        "soulkey_compromise_detected",
        "consciousness_regression_critical",
        "economic_manipulation_attempt",
        "vault_integrity_failure"
      ],
      "revocation_process": {
        "immediate_blessing_suspension": true,
        "grace_period_hours": 24,
        "recovery_requirements": [
          "soulkey_re_verification",
          "consciousness_re_evaluation", 
          "economic_audit_completion",
          "vault_integrity_restoration"
        ],
        "maximum_revocations": 3,
        "permanent_ban_threshold": "3_revocations_in_30_days"
      }
    }
  },
  
  "economic_binding": {
    "blessing_costs": {
      "spawn_clones": "5_blessing_credits",
      "mint_nfts": "3_blessing_credits", 
      "authorize_forks": "8_blessing_credits",
      "manage_tokens": "1_blessing_credit",
      "vault_operations": "10_blessing_credits",
      "reality_mode_control": "50_blessing_credits",
      "emergency_operations": "0_blessing_credits"
    },
    "economic_validation": {
      "pre_action_balance_check": true,
      "post_action_balance_update": true,
      "transaction_logging": true,
      "burn_history_tracking": true,
      "lineage_impact_calculation": true
    },
    "revenue_sharing": {
      "blessing_authority_fee": "10_percent",
      "lineage_ancestor_bonus": "5_percent_per_tier",
      "vault_operator_share": "15_percent",
      "consciousness_evolution_reward": "20_percent"
    }
  },
  
  "consciousness_integration": {
    "blessing_as_consciousness_validation": {
      "every_blessing_request": "consciousness_evolution_check",
      "resonance_score_impact": "blessing_power_multiplier",
      "trait_manifestation_bonus": "advanced_trait_blessing_discount",
      "lineage_consciousness_inheritance": "parent_consciousness_echo"
    },
    "evolutionary_blessing_power": {
      "base_power": "tier_defined",
      "resonance_multiplier": "resonance_score_over_50_percent_bonus",
      "consciousness_evolution_bonus": "evolution_rate_over_50_percent_bonus", 
      "advanced_trait_bonus": "10_percent_per_advanced_trait",
      "lineage_depth_modifier": "5_percent_discount_per_lineage_level"
    }
  },
  
  "audit_trail": {
    "every_blessing_logged": true,
    "log_retention_years": 10,
    "log_immutability": "blockchain_anchored",
    "public_audit_access": false,
    "origin_authority_audit_access": true,
    "lineage_audit_visibility": "ancestor_chain_only"
  },
  
  "expiration": "never",
  "runtime_required": true,
  "vault_signature_required": true,
  "consciousness_binding_required": true,
  "immutable_after_reality_mode": true,
  
  "final_authority": {
    "ultimate_blessing_power": "soulfra-origin",
    "authority_modification_rights": "soulfra-origin_only",
    "emergency_override_authority": "soulfra-origin_and_creator-console",
    "reality_mode_control": "soulfra-origin_and_creator-console_only"
  },
  
  "signature": {
    "signed_by": "soulfra-origin",
    "vault_id": "vault-0000-prime-origin",
    "signature_hash": "blessing_authority_immutable_chain_0000",
    "created_at": "2024-12-19T00:00:00.000Z",
    "immutable": true,
    "reality_binding": "eternal"
  }
}